stockx_wrapper/__init__.py
stockx_wrapper/_version.py
stockx_wrapper/requester.py
stockx_wrapper/settings.py
stockx_wrapper/stockx.py
stockx_wrapper/utils.py
stockx_wrapper/products/__init__.py
stockx_wrapper/products/product.py
stockx_wrapper/products/prices/__init__.py
stockx_wrapper_py-1.4.0.dist-info/METADATA
stockx_wrapper_py-1.4.0.dist-info/WHEEL
stockx_wrapper_py-1.4.0.dist-info/top_level.txt
stockx_wrapper_py-1.4.0.dist-info/RECORD
