Metadata-Version: 2.1
Name: stockx-wrapper-py
Version: 1.4.0
Summary: Simple Stockx Api for python 3
Home-page: https://github.com/EduardoHerreraM/stockx-wrapper-py
Author: EduardoHerreraM
License: UNKNOWN
Platform: UNKNOWN
Classifier: Programming Language :: Python :: 3
Classifier: Programming Language :: Python :: 3.6
Requires-Dist: requests
